lune/0.png
lune/1.png
lune/10.png
lune/11.png
lune/12.png
lune/13.png
lune/14.png
lune/15.png
lune/16.png
lune/17.png
lune/18.png
lune/19.png
lune/2.png
lune/20.png
lune/21.png
lune/22.png
lune/23.png
lune/24.png
lune/25.png
lune/26.png
lune/27.png
lune/28.png
lune/29.png
lune/3.png
lune/4.png
lune/5.png
lune/6.png
lune/7.png
lune/8.png
lune/9.png
lune/KELLER Stephane.jpg
lune/__init__.py
lune/phase.py
lune-1.6.4.dist-info/LICENCE
lune-1.6.4.dist-info/METADATA
lune-1.6.4.dist-info/WHEEL
lune-1.6.4.dist-info/entry_points.txt
lune-1.6.4.dist-info/top_level.txt
lune-1.6.4.dist-info/RECORD
