Metadata-Version: 2.1
Name: lune
Version: 1.6.4
Summary: From a date given in parameter, the algorithm returns dates for the new moon ; the first quarter ; the full moon and the last quarter
Home-page: https://github.com/KELLERStephane/KELLER-Stephane-Tests2maths/tree/master/7%20-%20Raspberry%20Pi/Ressources/lune
Author: KELLER Stephane
Author-email: stephane.keller@yahoo.com
License: WTFPL
Platform: UNKNOWN
Classifier: Programming Language :: Python
Classifier: Development Status :: 6 - Mature
Classifier: License :: OSI Approved
Classifier: Natural Language :: English
Classifier: Operating System :: OS Independent
Classifier: Programming Language :: Python :: 3.7
Classifier: Topic :: Education
